combinational_circuits/src/barrel_shifter.v

module barrel_shifter_4bit (
    input  [3:0] data,
    input  [1:0] shamt,
    input        dir,     
    output [3:0] result
);
    assign result = dir ? (data >> shamt) : (data << shamt);
endmodule

combinational_circuits/tb/tb_barrel_shifter.v
`timescale 1ns/1ps
module tb_barrel_shifter;
    reg  [3:0] data;
    reg  [1:0] shamt;
    reg        dir;
    wire [3:0] result;

    barrel_shifter_4bit uut (.data(data),.shamt(shamt),.dir(dir),.result(result));

    initial begin
        $dumpfile("barrel_shifter.vcd");
        $dumpvars(0, tb_barrel_shifter);
        data = 4'b1011;
        $display("=== Left Shifts ===");
        dir = 0;
        shamt=0; #10; $display("data=%b << %0d = %b", data, shamt, result);
        shamt=1; #10; $display("data=%b << %0d = %b", data, shamt, result);
        shamt=2; #10; $display("data=%b << %0d = %b", data, shamt, result);
        shamt=3; #10; $display("data=%b << %0d = %b", data, shamt, result);
        $display("=== Right Shifts ===");
        dir = 1;
        shamt=0; #10; $display("data=%b >> %0d = %b", data, shamt, result);
        shamt=1; #10; $display("data=%b >> %0d = %b", data, shamt, result);
        shamt=2; #10; $display("data=%b >> %0d = %b", data, shamt, result);
        shamt=3; #10; $display("data=%b >> %0d = %b", data, shamt, result);
        $finish;
    end
endmodule

combinational_circuits/barrel_shifter.vcd
$date
	Sun Apr 12 23:57:42 2026
$end
$version
	Icarus Verilog
$end
$timescale
	1ps
$end
$scope module tb_barrel_shifter $end
$var wire 4 ! result [3:0] $end
$var reg 4 " data [3:0] $end
$var reg 1 # dir $end
$var reg 2 $ shamt [1:0] $end
$scope module uut $end
$var wire 4 % data [3:0] $end
$var wire 1 # dir $end
$var wire 2 & shamt [1:0] $end
$var wire 4 ' result [3:0] $end
$upscope $end
$upscope $end
$enddefinitions $end
$comment Show the parameter values. $end
$dumpall
$end
#0
$dumpvars
b1011 '
b0 &
b1011 %
b0 $
0#
b1011 "
b1011 !
$end
#10000
b110 !
b110 '
b1 $
b1 &
#20000
b1100 !
b1100 '
b10 $
b10 &
#30000
b1000 !
b1000 '
b11 $
b11 &
#40000
b1011 !
b1011 '
b0 $
b0 &
1#
#50000
b101 !
b101 '
b1 $
b1 &
#60000
b10 !
b10 '
b10 $
b10 &
#70000
b1 !
b1 '
b11 $
b11 &
