combinational_circuits/src/CLA_4.v

module cla_generator (
    input  [3:0] G, P,   // per-bit generate/propagate
    input        Cin,
    output [3:0] C        // carry out per bit
);
    assign C[0] = G[0] | (P[0] & Cin);
    assign C[1] = G[1] | (P[1] & G[0]) | (P[1] & P[0] & Cin);
    assign C[2] = G[2] | (P[2] & G[1]) | (P[2] & P[1] & G[0]) | (P[2] & P[1] & P[0] & Cin);
    assign C[3] = G[3] | (P[3] & G[2]) | (P[3] & P[2] & G[1]) |
                  (P[3] & P[2] & P[1] & G[0]) | (P[3] & P[2] & P[1] & P[0] & Cin);
endmodule

module cla_adder_4bit (
    input  [3:0] A, B,
    input        Cin,
    output [3:0] Sum,
    output       Cout
);
    wire [3:0] G, P, C;

    assign G = A & B;      
    assign P = A ^ B;       

    cla_generator cla (.G(G), .P(P), .Cin(Cin), .C(C));

    assign Sum[0] = P[0] ^ Cin;
    assign Sum[1] = P[1] ^ C[0];
    assign Sum[2] = P[2] ^ C[1];
    assign Sum[3] = P[3] ^ C[2];
    assign Cout   = C[3];
endmodule

combinational_circuits/tb/tb_CLA_4.v
`timescale 1ns/1ps
module tb_cla;
    reg  [3:0] A, B;
    reg        Cin;
    wire [3:0] Sum;
    wire       Cout;

    cla_adder_4bit uut (.A(A), .B(B), .Cin(Cin), .Sum(Sum), .Cout(Cout));

    integer i, j;
    integer errors = 0;
    initial begin
        $dumpfile("cla.vcd");
        $dumpvars(0, tb_cla);
        for (i = 0; i < 16; i = i + 1) begin
            for (j = 0; j < 16; j = j + 1) begin
                A = i; B = j; Cin = 0; #10;
                if ({Cout, Sum} !== (A + B)) begin
                    $display("ERROR: %0d + %0d = %0d (expected %0d)", A, B, {Cout,Sum}, A+B);
                    errors = errors + 1;
                end
            end
        end
        if (errors == 0)
            $display("ALL TESTS PASSED for CLA 4-bit Adder");
        else
            $display("%0d ERRORS", errors);
        $finish;
    end
endmodule

combinational_circuits/cla.vcd
$date
	Mon Apr 13 00:01:28 2026
$end
$version
	Icarus Verilog
$end
$timescale
	1ps
$end
$scope module tb_cla $end
$var wire 4 ! Sum [3:0] $end
$var wire 1 " Cout $end
$var reg 4 # A [3:0] $end
$var reg 4 $ B [3:0] $end
$var reg 1 % Cin $end
$var integer 32 & errors [31:0] $end
$var integer 32 ' i [31:0] $end
$var integer 32 ( j [31:0] $end
$scope module uut $end
$var wire 4 ) A [3:0] $end
$var wire 4 * B [3:0] $end
$var wire 1 % Cin $end
$var wire 4 + G [3:0] $end
$var wire 4 , P [3:0] $end
$var wire 4 - Sum [3:0] $end
$var wire 1 " Cout $end
$var wire 4 . C [3:0] $end
$scope module cla $end
$var wire 1 % Cin $end
$var wire 4 / G [3:0] $end
$var wire 4 0 P [3:0] $end
$var wire 4 1 C [3:0] $end
$upscope $end
$upscope $end
$upscope $end
$enddefinitions $end
$comment Show the parameter values. $end
$dumpall
$end
#0
$dumpvars
b0 1
b0 0
b0 /
b0 .
b0 -
b0 ,
b0 +
b0 *
b0 )
b0 (
b0 '
b0 &
0%
b0 $
b0 #
0"
b0 !
$end
#10000
b1 !
b1 -
b1 ,
b1 0
b1 $
b1 *
b1 (
#20000
b10 !
b10 -
b10 ,
b10 0
b10 $
b10 *
b10 (
#30000
b11 !
b11 -
b11 ,
b11 0
b11 $
b11 *
b11 (
#40000
b100 !
b100 -
b100 ,
b100 0
b100 $
b100 *
b100 (
#50000
b101 !
b101 -
b101 ,
b101 0
b101 $
b101 *
b101 (
#60000
b110 !
b110 -
b110 ,
b110 0
b110 $
b110 *
b110 (
#70000
b111 !
b111 -
b111 ,
b111 0
b111 $
b111 *
b111 (
#80000
b1000 !
b1000 -
b1000 ,
b1000 0
b1000 $
b1000 *
b1000 (
#90000
b1001 !
b1001 -
b1001 ,
b1001 0
b1001 $
b1001 *
b1001 (
#100000
b1010 !
b1010 -
b1010 ,
b1010 0
b1010 $
b1010 *
b1010 (
#110000
b1011 !
b1011 -
b1011 ,
b1011 0
b1011 $
b1011 *
b1011 (
#120000
b1100 !
b1100 -
b1100 ,
b1100 0
b1100 $
b1100 *
b1100 (
#130000
b1101 !
b1101 -
b1101 ,
b1101 0
b1101 $
b1101 *
b1101 (
#140000
b1110 !
b1110 -
b1110 ,
b1110 0
b1110 $
b1110 *
b1110 (
#150000
b1111 !
b1111 -
b1111 ,
b1111 0
b1111 $
b1111 *
b1111 (
#160000
b1 !
b1 -
b1 ,
b1 0
b0 $
b0 *
b1 #
b1 )
b1 '
b0 (
#170000
b1 .
b1 1
b10 !
b10 -
b1 +
b1 /
b0 ,
b0 0
b1 $
b1 *
b1 (
#180000
b0 .
b0 1
b11 !
b11 -
b0 +
b0 /
b11 ,
b11 0
b10 $
b10 *
b10 (
#190000
b11 .
b11 1
b100 !
b100 -
b1 +
b1 /
b10 ,
b10 0
b11 $
b11 *
b11 (
#200000
b0 .
b0 1
b101 !
b101 -
b0 +
b0 /
b101 ,
b101 0
b100 $
b100 *
b100 (
#210000
b1 .
b1 1
b110 !
b110 -
b1 +
b1 /
b100 ,
b100 0
b101 $
b101 *
b101 (
#220000
b0 .
b0 1
b111 !
b111 -
b0 +
b0 /
b111 ,
b111 0
b110 $
b110 *
b110 (
#230000
b111 .
b111 1
b1000 !
b1000 -
b1 +
b1 /
b110 ,
b110 0
b111 $
b111 *
b111 (
#240000
b0 .
b0 1
b1001 !
b1001 -
b0 +
b0 /
b1001 ,
b1001 0
b1000 $
b1000 *
b1000 (
#250000
b1 .
b1 1
b1010 !
b1010 -
b1 +
b1 /
b1000 ,
b1000 0
b1001 $
b1001 *
b1001 (
#260000
b0 .
b0 1
b1011 !
b1011 -
b0 +
b0 /
b1011 ,
b1011 0
b1010 $
b1010 *
b1010 (
#270000
b11 .
b11 1
b1100 !
b1100 -
b1 +
b1 /
b1010 ,
b1010 0
b1011 $
b1011 *
b1011 (
#280000
b0 .
b0 1
b1101 !
b1101 -
b0 +
b0 /
b1101 ,
b1101 0
b1100 $
b1100 *
b1100 (
#290000
b1 .
b1 1
b1110 !
b1110 -
b1 +
b1 /
b1100 ,
b1100 0
b1101 $
b1101 *
b1101 (
#300000
b0 .
b0 1
b1111 !
b1111 -
b0 +
b0 /
b1111 ,
b1111 0
b1110 $
b1110 *
b1110 (
#310000
1"
b1111 .
b1111 1
b0 !
b0 -
b1 +
b1 /
b1110 ,
b1110 0
b1111 $
b1111 *
b1111 (
#320000
0"
b0 .
b0 1
b10 !
b10 -
b0 +
b0 /
b10 ,
b10 0
b0 $
b0 *
b10 #
b10 )
b10 '
b0 (
#330000
b11 !
b11 -
b11 ,
b11 0
b1 $
b1 *
b1 (
#340000
b10 .
b10 1
b100 !
b100 -
b10 +
b10 /
b0 ,
b0 0
b10 $
b10 *
b10 (
#350000
b101 !
b101 -
b1 ,
b1 0
b11 $
b11 *
b11 (
#360000
b0 .
b0 1
b110 !
b110 -
b0 +
b0 /
b110 ,
b110 0
b100 $
b100 *
b100 (
#370000
b111 !
b111 -
b111 ,
b111 0
b101 $
b101 *
b101 (
#380000
b110 .
b110 1
b1000 !
b1000 -
b10 +
b10 /
b100 ,
b100 0
b110 $
b110 *
b110 (
#390000
b1001 !
b1001 -
b101 ,
b101 0
b111 $
b111 *
b111 (
#400000
b0 .
b0 1
b1010 !
b1010 -
b0 +
b0 /
b1010 ,
b1010 0
b1000 $
b1000 *
b1000 (
#410000
b1011 !
b1011 -
b1011 ,
b1011 0
b1001 $
b1001 *
b1001 (
#420000
b10 .
b10 1
b1100 !
b1100 -
b10 +
b10 /
b1000 ,
b1000 0
b1010 $
b1010 *
b1010 (
#430000
b1101 !
b1101 -
b1001 ,
b1001 0
b1011 $
b1011 *
b1011 (
#440000
b0 .
b0 1
b1110 !
b1110 -
b0 +
b0 /
b1110 ,
b1110 0
b1100 $
b1100 *
b1100 (
#450000
b1111 !
b1111 -
b1111 ,
b1111 0
b1101 $
b1101 *
b1101 (
#460000
1"
b1110 .
b1110 1
b0 !
b0 -
b10 +
b10 /
b1100 ,
b1100 0
b1110 $
b1110 *
b1110 (
#470000
b1 !
b1 -
b1101 ,
b1101 0
b1111 $
b1111 *
b1111 (
#480000
0"
b0 .
b0 1
b11 !
b11 -
b0 +
b0 /
b11 ,
b11 0
b0 $
b0 *
b11 #
b11 )
b11 '
b0 (
#490000
b11 .
b11 1
b100 !
b100 -
b1 +
b1 /
b10 ,
b10 0
b1 $
b1 *
b1 (
#500000
b10 .
b10 1
b101 !
b101 -
b10 +
b10 /
b1 ,
b1 0
b10 $
b10 *
b10 (
#510000
b11 .
b11 1
b110 !
b110 -
b11 +
b11 /
b0 ,
b0 0
b11 $
b11 *
b11 (
#520000
b0 .
b0 1
b111 !
b111 -
b0 +
b0 /
b111 ,
b111 0
b100 $
b100 *
b100 (
#530000
b111 .
b111 1
b1000 !
b1000 -
b1 +
b1 /
b110 ,
b110 0
b101 $
b101 *
b101 (
#540000
b110 .
b110 1
b1001 !
b1001 -
b10 +
b10 /
b101 ,
b101 0
b110 $
b110 *
b110 (
#550000
b111 .
b111 1
b1010 !
b1010 -
b11 +
b11 /
b100 ,
b100 0
b111 $
b111 *
b111 (
#560000
b0 .
b0 1
b1011 !
b1011 -
b0 +
b0 /
b1011 ,
b1011 0
b1000 $
b1000 *
b1000 (
#570000
b11 .
b11 1
b1100 !
b1100 -
b1 +
b1 /
b1010 ,
b1010 0
b1001 $
b1001 *
b1001 (
#580000
b10 .
b10 1
b1101 !
b1101 -
b10 +
b10 /
b1001 ,
b1001 0
b1010 $
b1010 *
b1010 (
#590000
b11 .
b11 1
b1110 !
b1110 -
b11 +
b11 /
b1000 ,
b1000 0
b1011 $
b1011 *
b1011 (
#600000
b0 .
b0 1
b1111 !
b1111 -
b0 +
b0 /
b1111 ,
b1111 0
b1100 $
b1100 *
b1100 (
#610000
1"
b1111 .
b1111 1
b0 !
b0 -
b1 +
b1 /
b1110 ,
b1110 0
b1101 $
b1101 *
b1101 (
#620000
1"
b1110 .
b1110 1
b1 !
b1 -
b10 +
b10 /
b1101 ,
b1101 0
b1110 $
b1110 *
b1110 (
#630000
b1111 .
b1111 1
b10 !
b10 -
b11 +
b11 /
b1100 ,
b1100 0
b1111 $
b1111 *
b1111 (
#640000
0"
b0 .
b0 1
b100 !
b100 -
b0 +
b0 /
b100 ,
b100 0
b0 $
b0 *
b100 #
b100 )
b100 '
b0 (
#650000
b101 !
b101 -
b101 ,
b101 0
b1 $
b1 *
b1 (
#660000
b110 !
b110 -
b110 ,
b110 0
b10 $
b10 *
b10 (
#670000
b111 !
b111 -
b111 ,
b111 0
b11 $
b11 *
b11 (
#680000
b100 .
b100 1
b1000 !
b1000 -
b100 +
b100 /
b0 ,
b0 0
b100 $
b100 *
b100 (
#690000
b1001 !
b1001 -
b1 ,
b1 0
b101 $
b101 *
b101 (
#700000
b1010 !
b1010 -
b10 ,
b10 0
b110 $
b110 *
b110 (
#710000
b1011 !
b1011 -
b11 ,
b11 0
b111 $
b111 *
b111 (
#720000
b0 .
b0 1
b1100 !
b1100 -
b0 +
b0 /
b1100 ,
b1100 0
b1000 $
b1000 *
b1000 (
#730000
b1101 !
b1101 -
b1101 ,
b1101 0
b1001 $
b1001 *
b1001 (
#740000
b1110 !
b1110 -
b1110 ,
b1110 0
b1010 $
b1010 *
b1010 (
#750000
b1111 !
b1111 -
b1111 ,
b1111 0
b1011 $
b1011 *
b1011 (
#760000
1"
b1100 .
b1100 1
b0 !
b0 -
b100 +
b100 /
b1000 ,
b1000 0
b1100 $
b1100 *
b1100 (
#770000
b1 !
b1 -
b1001 ,
b1001 0
b1101 $
b1101 *
b1101 (
#780000
b10 !
b10 -
b1010 ,
b1010 0
b1110 $
b1110 *
b1110 (
#790000
b11 !
b11 -
b1011 ,
b1011 0
b1111 $
b1111 *
b1111 (
#800000
0"
b0 .
b0 1
b101 !
b101 -
b0 +
b0 /
b101 ,
b101 0
b0 $
b0 *
b101 #
b101 )
b101 '
b0 (
#810000
b1 .
b1 1
b110 !
b110 -
b1 +
b1 /
b100 ,
b100 0
b1 $
b1 *
b1 (
#820000
b0 .
b0 1
b111 !
b111 -
b0 +
b0 /
b111 ,
b111 0
b10 $
b10 *
b10 (
#830000
b111 .
b111 1
b1000 !
b1000 -
b1 +
b1 /
b110 ,
b110 0
b11 $
b11 *
b11 (
#840000
b100 .
b100 1
b1001 !
b1001 -
b100 +
b100 /
b1 ,
b1 0
b100 $
b100 *
b100 (
#850000
b101 .
b101 1
b1010 !
b1010 -
b101 +
b101 /
b0 ,
b0 0
b101 $
b101 *
b101 (
#860000
b100 .
b100 1
b1011 !
b1011 -
b100 +
b100 /
b11 ,
b11 0
b110 $
b110 *
b110 (
#870000
b111 .
b111 1
b1100 !
b1100 -
b101 +
b101 /
b10 ,
b10 0
b111 $
b111 *
b111 (
#880000
b0 .
b0 1
b1101 !
b1101 -
b0 +
b0 /
b1101 ,
b1101 0
b1000 $
b1000 *
b1000 (
#890000
b1 .
b1 1
b1110 !
b1110 -
b1 +
b1 /
b1100 ,
b1100 0
b1001 $
b1001 *
b1001 (
#900000
b0 .
b0 1
b1111 !
b1111 -
b0 +
b0 /
b1111 ,
b1111 0
b1010 $
b1010 *
b1010 (
#910000
1"
b1111 .
b1111 1
b0 !
b0 -
b1 +
b1 /
b1110 ,
b1110 0
b1011 $
b1011 *
b1011 (
#920000
1"
b1100 .
b1100 1
b1 !
b1 -
b100 +
b100 /
b1001 ,
b1001 0
b1100 $
b1100 *
b1100 (
#930000
b1101 .
b1101 1
b10 !
b10 -
b101 +
b101 /
b1000 ,
b1000 0
b1101 $
b1101 *
b1101 (
#940000
b1100 .
b1100 1
b11 !
b11 -
b100 +
b100 /
b1011 ,
b1011 0
b1110 $
b1110 *
b1110 (
#950000
b1111 .
b1111 1
b100 !
b100 -
b101 +
b101 /
b1010 ,
b1010 0
b1111 $
b1111 *
b1111 (
#960000
0"
b0 .
b0 1
b110 !
b110 -
b0 +
b0 /
b110 ,
b110 0
b0 $
b0 *
b110 #
b110 )
b110 '
b0 (
#970000
b111 !
b111 -
b111 ,
b111 0
b1 $
b1 *
b1 (
#980000
b110 .
b110 1
b1000 !
b1000 -
b10 +
b10 /
b100 ,
b100 0
b10 $
b10 *
b10 (
#990000
b1001 !
b1001 -
b101 ,
b101 0
b11 $
b11 *
b11 (
#1000000
b100 .
b100 1
b1010 !
b1010 -
b100 +
b100 /
b10 ,
b10 0
b100 $
b100 *
b100 (
#1010000
b1011 !
b1011 -
b11 ,
b11 0
b101 $
b101 *
b101 (
#1020000
b110 .
b110 1
b1100 !
b1100 -
b110 +
b110 /
b0 ,
b0 0
b110 $
b110 *
b110 (
#1030000
b1101 !
b1101 -
b1 ,
b1 0
b111 $
b111 *
b111 (
#1040000
b0 .
b0 1
b1110 !
b1110 -
b0 +
b0 /
b1110 ,
b1110 0
b1000 $
b1000 *
b1000 (
#1050000
b1111 !
b1111 -
b1111 ,
b1111 0
b1001 $
b1001 *
b1001 (
#1060000
1"
b1110 .
b1110 1
b0 !
b0 -
b10 +
b10 /
b1100 ,
b1100 0
b1010 $
b1010 *
b1010 (
#1070000
b1 !
b1 -
b1101 ,
b1101 0
b1011 $
b1011 *
b1011 (
#1080000
1"
b1100 .
b1100 1
b10 !
b10 -
b100 +
b100 /
b1010 ,
b1010 0
b1100 $
b1100 *
b1100 (
#1090000
b11 !
b11 -
b1011 ,
b1011 0
b1101 $
b1101 *
b1101 (
#1100000
b1110 .
b1110 1
b100 !
b100 -
b110 +
b110 /
b1000 ,
b1000 0
b1110 $
b1110 *
b1110 (
#1110000
b101 !
b101 -
b1001 ,
b1001 0
b1111 $
b1111 *
b1111 (
#1120000
0"
b0 .
b0 1
b111 !
b111 -
b0 +
b0 /
b111 ,
b111 0
b0 $
b0 *
b111 #
b111 )
b111 '
b0 (
#1130000
b111 .
b111 1
b1000 !
b1000 -
b1 +
b1 /
b110 ,
b110 0
b1 $
b1 *
b1 (
#1140000
b110 .
b110 1
b1001 !
b1001 -
b10 +
b10 /
b101 ,
b101 0
b10 $
b10 *
b10 (
#1150000
b111 .
b111 1
b1010 !
b1010 -
b11 +
b11 /
b100 ,
b100 0
b11 $
b11 *
b11 (
#1160000
b100 .
b100 1
b1011 !
b1011 -
b100 +
b100 /
b11 ,
b11 0
b100 $
b100 *
b100 (
#1170000
b111 .
b111 1
b1100 !
b1100 -
b101 +
b101 /
b10 ,
b10 0
b101 $
b101 *
b101 (
#1180000
b110 .
b110 1
b1101 !
b1101 -
b110 +
b110 /
b1 ,
b1 0
b110 $
b110 *
b110 (
#1190000
b111 .
b111 1
b1110 !
b1110 -
b111 +
b111 /
b0 ,
b0 0
b111 $
b111 *
b111 (
#1200000
b0 .
b0 1
b1111 !
b1111 -
b0 +
b0 /
b1111 ,
b1111 0
b1000 $
b1000 *
b1000 (
#1210000
1"
b1111 .
b1111 1
b0 !
b0 -
b1 +
b1 /
b1110 ,
b1110 0
b1001 $
b1001 *
b1001 (
#1220000
1"
b1110 .
b1110 1
b1 !
b1 -
b10 +
b10 /
b1101 ,
b1101 0
b1010 $
b1010 *
b1010 (
#1230000
b1111 .
b1111 1
b10 !
b10 -
b11 +
b11 /
b1100 ,
b1100 0
b1011 $
b1011 *
b1011 (
#1240000
1"
b1100 .
b1100 1
b11 !
b11 -
b100 +
b100 /
b1011 ,
b1011 0
b1100 $
b1100 *
b1100 (
#1250000
b1111 .
b1111 1
b100 !
b100 -
b101 +
b101 /
b1010 ,
b1010 0
b1101 $
b1101 *
b1101 (
#1260000
b1110 .
b1110 1
b101 !
b101 -
b110 +
b110 /
b1001 ,
b1001 0
b1110 $
b1110 *
b1110 (
#1270000
b1111 .
b1111 1
b110 !
b110 -
b111 +
b111 /
b1000 ,
b1000 0
b1111 $
b1111 *
b1111 (
#1280000
0"
b1000 !
b1000 -
b0 .
b0 1
b0 +
b0 /
b0 $
b0 *
b1000 #
b1000 )
b1000 '
b0 (
#1290000
b1001 !
b1001 -
b1001 ,
b1001 0
b1 $
b1 *
b1 (
#1300000
b1010 !
b1010 -
b1010 ,
b1010 0
b10 $
b10 *
b10 (
#1310000
b1011 !
b1011 -
b1011 ,
b1011 0
b11 $
b11 *
b11 (
#1320000
b1100 !
b1100 -
b1100 ,
b1100 0
b100 $
b100 *
b100 (
#1330000
b1101 !
b1101 -
b1101 ,
b1101 0
b101 $
b101 *
b101 (
#1340000
b1110 !
b1110 -
b1110 ,
b1110 0
b110 $
b110 *
b110 (
#1350000
b1111 !
b1111 -
b1111 ,
b1111 0
b111 $
b111 *
b111 (
#1360000
1"
b1000 .
b1000 1
b0 !
b0 -
b1000 +
b1000 /
b0 ,
b0 0
b1000 $
b1000 *
b1000 (
#1370000
b1 !
b1 -
b1 ,
b1 0
b1001 $
b1001 *
b1001 (
#1380000
b10 !
b10 -
b10 ,
b10 0
b1010 $
b1010 *
b1010 (
#1390000
b11 !
b11 -
b11 ,
b11 0
b1011 $
b1011 *
b1011 (
#1400000
b100 !
b100 -
b100 ,
b100 0
b1100 $
b1100 *
b1100 (
#1410000
b101 !
b101 -
b101 ,
b101 0
b1101 $
b1101 *
b1101 (
#1420000
b110 !
b110 -
b110 ,
b110 0
b1110 $
b1110 *
b1110 (
#1430000
b111 !
b111 -
b111 ,
b111 0
b1111 $
b1111 *
b1111 (
#1440000
0"
b0 .
b0 1
b1001 !
b1001 -
b0 +
b0 /
b1001 ,
b1001 0
b0 $
b0 *
b1001 #
b1001 )
b1001 '
b0 (
#1450000
b1 .
b1 1
b1010 !
b1010 -
b1 +
b1 /
b1000 ,
b1000 0
b1 $
b1 *
b1 (
#1460000
b0 .
b0 1
b1011 !
b1011 -
b0 +
b0 /
b1011 ,
b1011 0
b10 $
b10 *
b10 (
#1470000
b11 .
b11 1
b1100 !
b1100 -
b1 +
b1 /
b1010 ,
b1010 0
b11 $
b11 *
b11 (
#1480000
b0 .
b0 1
b1101 !
b1101 -
b0 +
b0 /
b1101 ,
b1101 0
b100 $
b100 *
b100 (
#1490000
b1 .
b1 1
b1110 !
b1110 -
b1 +
b1 /
b1100 ,
b1100 0
b101 $
b101 *
b101 (
#1500000
b0 .
b0 1
b1111 !
b1111 -
b0 +
b0 /
b1111 ,
b1111 0
b110 $
b110 *
b110 (
#1510000
1"
b1111 .
b1111 1
b0 !
b0 -
b1 +
b1 /
b1110 ,
b1110 0
b111 $
b111 *
b111 (
#1520000
1"
b1000 .
b1000 1
b1 !
b1 -
b1000 +
b1000 /
b1 ,
b1 0
b1000 $
b1000 *
b1000 (
#1530000
b1001 .
b1001 1
b10 !
b10 -
b1001 +
b1001 /
b0 ,
b0 0
b1001 $
b1001 *
b1001 (
#1540000
b1000 .
b1000 1
b11 !
b11 -
b1000 +
b1000 /
b11 ,
b11 0
b1010 $
b1010 *
b1010 (
#1550000
b1011 .
b1011 1
b100 !
b100 -
b1001 +
b1001 /
b10 ,
b10 0
b1011 $
b1011 *
b1011 (
#1560000
b1000 .
b1000 1
b101 !
b101 -
b1000 +
b1000 /
b101 ,
b101 0
b1100 $
b1100 *
b1100 (
#1570000
b1001 .
b1001 1
b110 !
b110 -
b1001 +
b1001 /
b100 ,
b100 0
b1101 $
b1101 *
b1101 (
#1580000
b1000 .
b1000 1
b111 !
b111 -
b1000 +
b1000 /
b111 ,
b111 0
b1110 $
b1110 *
b1110 (
#1590000
b1111 .
b1111 1
b1000 !
b1000 -
b1001 +
b1001 /
b110 ,
b110 0
b1111 $
b1111 *
b1111 (
#1600000
0"
b0 .
b0 1
b1010 !
b1010 -
b0 +
b0 /
b1010 ,
b1010 0
b0 $
b0 *
b1010 #
b1010 )
b1010 '
b0 (
#1610000
b1011 !
b1011 -
b1011 ,
b1011 0
b1 $
b1 *
b1 (
#1620000
b10 .
b10 1
b1100 !
b1100 -
b10 +
b10 /
b1000 ,
b1000 0
b10 $
b10 *
b10 (
#1630000
b1101 !
b1101 -
b1001 ,
b1001 0
b11 $
b11 *
b11 (
#1640000
b0 .
b0 1
b1110 !
b1110 -
b0 +
b0 /
b1110 ,
b1110 0
b100 $
b100 *
b100 (
#1650000
b1111 !
b1111 -
b1111 ,
b1111 0
b101 $
b101 *
b101 (
#1660000
1"
b1110 .
b1110 1
b0 !
b0 -
b10 +
b10 /
b1100 ,
b1100 0
b110 $
b110 *
b110 (
#1670000
b1 !
b1 -
b1101 ,
b1101 0
b111 $
b111 *
b111 (
#1680000
b1000 .
b1000 1
b10 !
b10 -
b1000 +
b1000 /
b10 ,
b10 0
b1000 $
b1000 *
b1000 (
#1690000
b11 !
b11 -
b11 ,
b11 0
b1001 $
b1001 *
b1001 (
#1700000
b1010 .
b1010 1
b100 !
b100 -
b1010 +
b1010 /
b0 ,
b0 0
b1010 $
b1010 *
b1010 (
#1710000
b101 !
b101 -
b1 ,
b1 0
b1011 $
b1011 *
b1011 (
#1720000
b1000 .
b1000 1
b110 !
b110 -
b1000 +
b1000 /
b110 ,
b110 0
b1100 $
b1100 *
b1100 (
#1730000
b111 !
b111 -
b111 ,
b111 0
b1101 $
b1101 *
b1101 (
#1740000
b1110 .
b1110 1
b1000 !
b1000 -
b1010 +
b1010 /
b100 ,
b100 0
b1110 $
b1110 *
b1110 (
#1750000
b1001 !
b1001 -
b101 ,
b101 0
b1111 $
b1111 *
b1111 (
#1760000
0"
b0 .
b0 1
b1011 !
b1011 -
b0 +
b0 /
b1011 ,
b1011 0
b0 $
b0 *
b1011 #
b1011 )
b1011 '
b0 (
#1770000
b11 .
b11 1
b1100 !
b1100 -
b1 +
b1 /
b1010 ,
b1010 0
b1 $
b1 *
b1 (
#1780000
b10 .
b10 1
b1101 !
b1101 -
b10 +
b10 /
b1001 ,
b1001 0
b10 $
b10 *
b10 (
#1790000
b11 .
b11 1
b1110 !
b1110 -
b11 +
b11 /
b1000 ,
b1000 0
b11 $
b11 *
b11 (
#1800000
b0 .
b0 1
b1111 !
b1111 -
b0 +
b0 /
b1111 ,
b1111 0
b100 $
b100 *
b100 (
#1810000
1"
b1111 .
b1111 1
b0 !
b0 -
b1 +
b1 /
b1110 ,
b1110 0
b101 $
b101 *
b101 (
#1820000
1"
b1110 .
b1110 1
b1 !
b1 -
b10 +
b10 /
b1101 ,
b1101 0
b110 $
b110 *
b110 (
#1830000
b1111 .
b1111 1
b10 !
b10 -
b11 +
b11 /
b1100 ,
b1100 0
b111 $
b111 *
b111 (
#1840000
b1000 .
b1000 1
b11 !
b11 -
b1000 +
b1000 /
b11 ,
b11 0
b1000 $
b1000 *
b1000 (
#1850000
b1011 .
b1011 1
b100 !
b100 -
b1001 +
b1001 /
b10 ,
b10 0
b1001 $
b1001 *
b1001 (
#1860000
b1010 .
b1010 1
b101 !
b101 -
b1010 +
b1010 /
b1 ,
b1 0
b1010 $
b1010 *
b1010 (
#1870000
b1011 .
b1011 1
b110 !
b110 -
b1011 +
b1011 /
b0 ,
b0 0
b1011 $
b1011 *
b1011 (
#1880000
b1000 .
b1000 1
b111 !
b111 -
b1000 +
b1000 /
b111 ,
b111 0
b1100 $
b1100 *
b1100 (
#1890000
b1111 .
b1111 1
b1000 !
b1000 -
b1001 +
b1001 /
b110 ,
b110 0
b1101 $
b1101 *
b1101 (
#1900000
b1110 .
b1110 1
b1001 !
b1001 -
b1010 +
b1010 /
b101 ,
b101 0
b1110 $
b1110 *
b1110 (
#1910000
b1111 .
b1111 1
b1010 !
b1010 -
b1011 +
b1011 /
b100 ,
b100 0
b1111 $
b1111 *
b1111 (
#1920000
0"
b0 .
b0 1
b1100 !
b1100 -
b0 +
b0 /
b1100 ,
b1100 0
b0 $
b0 *
b1100 #
b1100 )
b1100 '
b0 (
#1930000
b1101 !
b1101 -
b1101 ,
b1101 0
b1 $
b1 *
b1 (
#1940000
b1110 !
b1110 -
b1110 ,
b1110 0
b10 $
b10 *
b10 (
#1950000
b1111 !
b1111 -
b1111 ,
b1111 0
b11 $
b11 *
b11 (
#1960000
1"
b1100 .
b1100 1
b0 !
b0 -
b100 +
b100 /
b1000 ,
b1000 0
b100 $
b100 *
b100 (
#1970000
b1 !
b1 -
b1001 ,
b1001 0
b101 $
b101 *
b101 (
#1980000
b10 !
b10 -
b1010 ,
b1010 0
b110 $
b110 *
b110 (
#1990000
b11 !
b11 -
b1011 ,
b1011 0
b111 $
b111 *
b111 (
#2000000
b1000 .
b1000 1
b100 !
b100 -
b1000 +
b1000 /
b100 ,
b100 0
b1000 $
b1000 *
b1000 (
#2010000
b101 !
b101 -
b101 ,
b101 0
b1001 $
b1001 *
b1001 (
#2020000
b110 !
b110 -
b110 ,
b110 0
b1010 $
b1010 *
b1010 (
#2030000
b111 !
b111 -
b111 ,
b111 0
b1011 $
b1011 *
b1011 (
#2040000
b1100 .
b1100 1
b1000 !
b1000 -
b1100 +
b1100 /
b0 ,
b0 0
b1100 $
b1100 *
b1100 (
#2050000
b1001 !
b1001 -
b1 ,
b1 0
b1101 $
b1101 *
b1101 (
#2060000
b1010 !
b1010 -
b10 ,
b10 0
b1110 $
b1110 *
b1110 (
#2070000
b1011 !
b1011 -
b11 ,
b11 0
b1111 $
b1111 *
b1111 (
#2080000
0"
b0 .
b0 1
b1101 !
b1101 -
b0 +
b0 /
b1101 ,
b1101 0
b0 $
b0 *
b1101 #
b1101 )
b1101 '
b0 (
#2090000
b1 .
b1 1
b1110 !
b1110 -
b1 +
b1 /
b1100 ,
b1100 0
b1 $
b1 *
b1 (
#2100000
b0 .
b0 1
b1111 !
b1111 -
b0 +
b0 /
b1111 ,
b1111 0
b10 $
b10 *
b10 (
#2110000
1"
b1111 .
b1111 1
b0 !
b0 -
b1 +
b1 /
b1110 ,
b1110 0
b11 $
b11 *
b11 (
#2120000
1"
b1100 .
b1100 1
b1 !
b1 -
b100 +
b100 /
b1001 ,
b1001 0
b100 $
b100 *
b100 (
#2130000
b1101 .
b1101 1
b10 !
b10 -
b101 +
b101 /
b1000 ,
b1000 0
b101 $
b101 *
b101 (
#2140000
b1100 .
b1100 1
b11 !
b11 -
b100 +
b100 /
b1011 ,
b1011 0
b110 $
b110 *
b110 (
#2150000
b1111 .
b1111 1
b100 !
b100 -
b101 +
b101 /
b1010 ,
b1010 0
b111 $
b111 *
b111 (
#2160000
b1000 .
b1000 1
b101 !
b101 -
b1000 +
b1000 /
b101 ,
b101 0
b1000 $
b1000 *
b1000 (
#2170000
b1001 .
b1001 1
b110 !
b110 -
b1001 +
b1001 /
b100 ,
b100 0
b1001 $
b1001 *
b1001 (
#2180000
b1000 .
b1000 1
b111 !
b111 -
b1000 +
b1000 /
b111 ,
b111 0
b1010 $
b1010 *
b1010 (
#2190000
b1111 .
b1111 1
b1000 !
b1000 -
b1001 +
b1001 /
b110 ,
b110 0
b1011 $
b1011 *
b1011 (
#2200000
b1100 .
b1100 1
b1001 !
b1001 -
b1100 +
b1100 /
b1 ,
b1 0
b1100 $
b1100 *
b1100 (
#2210000
b1101 .
b1101 1
b1010 !
b1010 -
b1101 +
b1101 /
b0 ,
b0 0
b1101 $
b1101 *
b1101 (
#2220000
b1100 .
b1100 1
b1011 !
b1011 -
b1100 +
b1100 /
b11 ,
b11 0
b1110 $
b1110 *
b1110 (
#2230000
b1111 .
b1111 1
b1100 !
b1100 -
b1101 +
b1101 /
b10 ,
b10 0
b1111 $
b1111 *
b1111 (
#2240000
0"
b0 .
b0 1
b1110 !
b1110 -
b0 +
b0 /
b1110 ,
b1110 0
b0 $
b0 *
b1110 #
b1110 )
b1110 '
b0 (
#2250000
b1111 !
b1111 -
b1111 ,
b1111 0
b1 $
b1 *
b1 (
#2260000
1"
b1110 .
b1110 1
b0 !
b0 -
b10 +
b10 /
b1100 ,
b1100 0
b10 $
b10 *
b10 (
