combinational_circuits/src/bin_to_gray.v

module bin_to_gray #(parameter N = 4) (
    input  [N-1:0] B,
    output [N-1:0] G
);
    assign G = B ^ (B >> 1);
endmodule


module gray_to_bin #(parameter N = 4) (
    input  [N-1:0] G,
    output [N-1:0] B
);
    genvar i;
    assign B[N-1] = G[N-1];
    generate
        for (i = N-2; i >= 0; i = i - 1) begin : g2b
            assign B[i] = B[i+1] ^ G[i];
        end
    endgenerate
endmodule

combinational_circuits/tb/tb_bin_to_gray.v
`timescale 1ns/1ps
module tb_code_converters;
    reg  [3:0] B, G_in;
    wire [3:0] G_out, B_out;

    bin_to_gray b2g (.B(B), .G(G_out));
    gray_to_bin g2b (.G(G_in), .B(B_out));

    integer i;
    initial begin
        $dumpfile("code_converters.vcd");
        $dumpvars(0, tb_code_converters);
        $display("Binary | Gray  | Gray->Binary RoundTrip");
        $display("-------|-------|----------------------");
        for (i = 0; i < 16; i = i + 1) begin
            B = i; G_in = i ^ (i >> 1); #10;
            $display("%b    | %b  | %b", B, G_out, B_out);
        end
        $finish;
    end
endmodule

combinational_circuits/code_converters.vcd
$date
	Sun Apr 12 23:47:05 2026
$end
$version
	Icarus Verilog
$end
$timescale
	1ps
$end
$scope module tb_code_converters $end
$var wire 4 ! G_out [3:0] $end
$var wire 4 " B_out [3:0] $end
$var reg 4 # B [3:0] $end
$var reg 4 $ G_in [3:0] $end
$var integer 32 % i [31:0] $end
$scope module b2g $end
$var wire 4 & B [3:0] $end
$var wire 4 ' G [3:0] $end
$var parameter 32 ( N $end
$upscope $end
$scope module g2b $end
$var wire 4 ) G [3:0] $end
$var wire 4 * B [3:0] $end
$var parameter 32 + N $end
$scope begin g2b[0] $end
$var parameter 2 , i $end
$upscope $end
$scope begin g2b[1] $end
$var parameter 2 - i $end
$upscope $end
$scope begin g2b[2] $end
$var parameter 3 . i $end
$upscope $end
$upscope $end
$upscope $end
$enddefinitions $end
$comment Show the parameter values. $end
$dumpall
b10 .
b1 -
b0 ,
b100 +
b100 (
$end
#0
$dumpvars
b0 *
b0 )
b0 '
b0 &
b0 %
b0 $
b0 #
b0 "
b0 !
$end
#10000
b1 "
b1 *
b1 !
b1 '
b1 $
b1 )
b1 #
b1 &
b1 %
#20000
b10 "
b10 *
b11 !
b11 '
b11 $
b11 )
b10 #
b10 &
b10 %
#30000
b11 "
b11 *
b10 !
b10 '
b10 $
b10 )
b11 #
b11 &
b11 %
#40000
b100 "
b100 *
b110 !
b110 '
b110 $
b110 )
b100 #
b100 &
b100 %
#50000
b101 "
b101 *
b111 !
b111 '
b111 $
b111 )
b101 #
b101 &
b101 %
#60000
b110 "
b110 *
b101 !
b101 '
b101 $
b101 )
b110 #
b110 &
b110 %
#70000
b111 "
b111 *
b100 !
b100 '
b100 $
b100 )
b111 #
b111 &
b111 %
#80000
b1000 "
b1000 *
b1100 !
b1100 '
b1100 $
b1100 )
b1000 #
b1000 &
b1000 %
#90000
b1001 "
b1001 *
b1101 !
b1101 '
b1101 $
b1101 )
b1001 #
b1001 &
b1001 %
#100000
b1010 "
b1010 *
b1111 !
b1111 '
b1111 $
b1111 )
b1010 #
b1010 &
b1010 %
#110000
b1011 "
b1011 *
b1110 !
b1110 '
b1110 $
b1110 )
b1011 #
b1011 &
b1011 %
#120000
b1100 "
b1100 *
b1010 !
b1010 '
b1010 $
b1010 )
b1100 #
b1100 &
b1100 %
#130000
b1101 "
b1101 *
b1011 !
b1011 '
b1011 $
b1011 )
b1101 #
b1101 &
b1101 %
#140000
b1110 "
b1110 *
b1001 !
b1001 '
b1001 $
b1001 )
b1110 #
b1110 &
b1110 %
#150000
b1111 "
b1111 *
b1000 !
b1000 '
b1000 $
b1000 )
b1111 #
b1111 &
b1111 %
#160000
b10000 %
