combinational_circuits/src/decod_2to4.v

module decoder_2to4( 
    input [1:0] A,
    input            EN,
    output reg [3:0] Y
);
    always @(*) begin
        if (!EN)
            Y = 4'b0000;
        else
            Y = 4'b0001 << A;
    end
endmodule

module decoder_3to8 (
    input      [2:0] A,
    input            EN,
    output reg [7:0] Y
);
    always @(*) begin
        if (!EN)
            Y = 8'b00000000;
        else
            Y = 8'b00000001 << A;
    end
endmodule

combinational_circuits/tb/tb_decod_2to4.v
`timescale 1ns/1ps
module tb_decoders;

    
    reg  [1:0] A2;
    reg        EN2;
    wire [3:0] Y2;
    decoder_2to4 d2 (.A(A2), .EN(EN2), .Y(Y2));

    
    reg  [2:0] A3;
    reg        EN3;
    wire [7:0] Y3;
    decoder_3to8 d3 (.A(A3), .EN(EN3), .Y(Y3));

    integer i;
    initial begin
        $dumpfile("decoders.vcd");
        $dumpvars(0, tb_decoders);

        // 2-to-4
        $display("=== 2-to-4 Decoder ===");
        EN2 = 1;
        for (i = 0; i < 4; i = i + 1) begin
            A2 = i; #10;
            $display("A=%b EN=%b => Y=%b", A2, EN2, Y2);
        end
        EN2 = 0; A2 = 2; #10;
        $display("A=%b EN=%b => Y=%b (disabled)", A2, EN2, Y2);

        // 3-to-8
        $display("=== 3-to-8 Decoder ===");
        EN3 = 1;
        for (i = 0; i < 8; i = i + 1) begin
            A3 = i; #10;
            $display("A=%b EN=%b => Y=%b", A3, EN3, Y3);
        end
        $finish;
    end
endmodule

combinational_circuits/decoders.vcd
$date
	Sun Apr 12 22:12:16 2026
$end
$version
	Icarus Verilog
$end
$timescale
	1ps
$end
$scope module tb_decoders $end
$var wire 8 ! Y3 [7:0] $end
$var wire 4 " Y2 [3:0] $end
$var reg 2 # A2 [1:0] $end
$var reg 3 $ A3 [2:0] $end
$var reg 1 % EN2 $end
$var reg 1 & EN3 $end
$var integer 32 ' i [31:0] $end
$scope module d2 $end
$var wire 2 ( A [1:0] $end
$var wire 1 % EN $end
$var reg 4 ) Y [3:0] $end
$upscope $end
$scope module d3 $end
$var wire 3 * A [2:0] $end
$var wire 1 & EN $end
$var reg 8 + Y [7:0] $end
$upscope $end
$upscope $end
$enddefinitions $end
$comment Show the parameter values. $end
$dumpall
$end
#0
$dumpvars
bx +
bx *
b1 )
b0 (
b0 '
x&
1%
bx $
b0 #
b1 "
bx !
$end
#10000
b10 "
b10 )
b1 #
b1 (
b1 '
#20000
b100 "
b100 )
b10 #
b10 (
b10 '
#30000
b1000 "
b1000 )
b11 #
b11 (
b11 '
#40000
b0 "
b0 )
b10 #
b10 (
0%
b100 '
#50000
b1 !
b1 +
b0 $
b0 *
b0 '
1&
#60000
b10 !
b10 +
b1 $
b1 *
b1 '
#70000
b100 !
b100 +
b10 $
b10 *
b10 '
#80000
b1000 !
b1000 +
b11 $
b11 *
b11 '
#90000
b10000 !
b10000 +
b100 $
b100 *
b100 '
#100000
b100000 !
b100000 +
b101 $
b101 *
b101 '
#110000
b1000000 !
b1000000 +
b110 $
b110 *
b110 '
#120000
b10000000 !
b10000000 +
b111 $
b111 *
b111 '
#130000
b1000 '
