combinational_circuits/src/lfsr.v
module lfsr(input rst,clk,output reg [7:0]lfsr);
	wire feedback;
	assign feedback=lfsr[7]^lfsr[6]^lfsr[5]^lfsr[4];

	always @(posedge clk)begin
		if(rst)
			lfsr<=8'b00000001;
		else
			lfsr<={lfsr[6:0],feedback};
	end
endmodule

combinational_circuits/tb/tb_lfsr.v
`timescale 1ns/1ps

module tb_lfsr;

reg clk;
reg rst;
wire [7:0] lfsr;


lfsr  uut (
    .clk(clk),
    .rst(rst),
    .lfsr(lfsr)
);


always #5 clk = ~clk;

initial begin
    clk = 0;
    rst = 1;

    
    #10;
    rst = 0;

   
    #300;

    $finish;
end


initial begin
    $monitor("Time = %0t | LFSR = %b", $time, lfsr);
end


initial begin
    $dumpfile("lfsr.vcd");
    $dumpvars(0, tb_lfsr);
end

endmodule

combinational_circuits/lfsr.vcd
$date
	Wed Apr 15 09:58:51 2026
$end
$version
	Icarus Verilog
$end
$timescale
	1ps
$end
$scope module tb_lfsr $end
$var wire 8 ! lfsr [7:0] $end
$var reg 1 " clk $end
$var reg 1 # rst $end
$scope module uut $end
$var wire 1 " clk $end
$var wire 1 $ feedback $end
$var wire 1 # rst $end
$var reg 8 % lfsr [7:0] $end
$upscope $end
$upscope $end
$enddefinitions $end
$comment Show the parameter values. $end
$dumpall
$end
#0
$dumpvars
bx %
x$
1#
0"
bx !
$end
#5000
0$
b1 !
b1 %
1"
#10000
0"
0#
#15000
b10 !
b10 %
1"
#20000
0"
#25000
b100 !
b100 %
1"
#30000
0"
#35000
b1000 !
b1000 %
1"
#40000
0"
#45000
1$
b10000 !
b10000 %
1"
#50000
0"
#55000
1$
b100001 !
b100001 %
1"
#60000
0"
#65000
1$
b1000011 !
b1000011 %
1"
#70000
0"
#75000
b10000111 !
b10000111 %
1"
#80000
0"
#85000
0$
b1111 !
b1111 %
1"
#90000
0"
#95000
1$
b11110 !
b11110 %
1"
#100000
0"
#105000
0$
b111101 !
b111101 %
1"
#110000
0"
#115000
1$
b1111010 !
b1111010 %
1"
#120000
0"
#125000
0$
b11110101 !
b11110101 %
1"
#130000
0"
#135000
1$
b11101010 !
b11101010 %
1"
#140000
0"
#145000
1$
b11010101 !
b11010101 %
1"
#150000
0"
#155000
0$
b10101011 !
b10101011 %
1"
#160000
0"
#165000
0$
b1010110 !
b1010110 %
1"
#170000
0"
#175000
0$
b10101100 !
b10101100 %
1"
#180000
0"
#185000
0$
b1011000 !
b1011000 %
1"
#190000
0"
#195000
1$
b10110000 !
b10110000 %
1"
#200000
0"
#205000
0$
b1100001 !
b1100001 %
1"
#210000
0"
#215000
0$
b11000010 !
b11000010 %
1"
#220000
0"
#225000
1$
b10000100 !
b10000100 %
1"
#230000
0"
#235000
0$
b1001 !
b1001 %
1"
#240000
0"
#245000
1$
b10010 !
b10010 %
1"
#250000
0"
#255000
1$
b100101 !
b100101 %
1"
#260000
0"
#265000
1$
b1001011 !
b1001011 %
1"
#270000
0"
#275000
0$
b10010111 !
b10010111 %
1"
#280000
0"
#285000
1$
b101110 !
b101110 %
1"
#290000
0"
#295000
0$
b1011101 !
b1011101 %
1"
#300000
0"
#305000
1$
b10111010 !
b10111010 %
1"
