combinational_circuits/src/mux_8to1.v
module mux_4to1 (
    input  [3:0] d,
    input  [1:0] sel,
    output       y
);
    assign y = d[sel];
endmodule


module mux_8to1 (
    input  [7:0] d,
    input  [2:0] sel,
    output       y
);
    wire y0, y1;

   
    mux_4to1 m0 (.d(d[3:0]), .sel(sel[1:0]), .y(y0));

    
    mux_4to1 m1 (.d(d[7:4]), .sel(sel[1:0]), .y(y1));

   
    assign y = sel[2] ? y1 : y0;
endmodule

combinational_circuits/tb/tb_mux_8to1.v
`timescale 1ns/1ps
module tb_mux_8to1;
    reg  [7:0] d;
    reg  [2:0] sel;
    wire       y;

    mux_8to1 uut (.d(d), .sel(sel), .y(y));

    integer i;
    initial begin
        $dumpfile("mux_8to1.vcd");
        $dumpvars(0, tb_mux_8to1);
        d = 8'b10110100;
        $display("Input data: %b", d);
        for (i = 0; i < 8; i = i + 1) begin
            sel = i;
            #10;
            $display("sel=%0d => y=%b (expected d[%0d]=%b)", sel, y, i, d[i]);
        end
        $display("TEST PASSED");
        $finish;
    end
endmodule

combinational_circuits/mux_8to1.vcd
$date
	Sun Apr 12 19:39:23 2026
$end
$version
	Icarus Verilog
$end
$timescale
	1ps
$end
$scope module tb_mux_8to1 $end
$var wire 1 ! y $end
$var reg 8 " d [7:0] $end
$var reg 3 # sel [2:0] $end
$var integer 32 $ i [31:0] $end
$scope module uut $end
$var wire 8 % d [7:0] $end
$var wire 3 & sel [2:0] $end
$var wire 1 ' y1 $end
$var wire 1 ( y0 $end
$var wire 1 ! y $end
$scope module m0 $end
$var wire 4 ) d [3:0] $end
$var wire 2 * sel [1:0] $end
$var wire 1 ( y $end
$upscope $end
$scope module m1 $end
$var wire 4 + d [3:0] $end
$var wire 2 , sel [1:0] $end
$var wire 1 ' y $end
$upscope $end
$upscope $end
$upscope $end
$enddefinitions $end
$comment Show the parameter values. $end
$dumpall
$end
#0
$dumpvars
b0 ,
b1011 +
b0 *
b100 )
0(
1'
b0 &
b10110100 %
b0 $
b0 #
b10110100 "
0!
$end
#10000
b1 *
b1 ,
b1 #
b1 &
b1 $
#20000
1!
1(
b10 *
0'
b10 ,
b10 #
b10 &
b10 $
#30000
0!
0(
b11 *
1'
b11 ,
b11 #
b11 &
b11 $
#40000
1!
b0 *
b0 ,
b100 #
b100 &
b100 $
#50000
b1 *
b1 ,
b101 #
b101 &
b101 $
#60000
0!
1(
b10 *
0'
b10 ,
b110 #
b110 &
b110 $
#70000
1!
0(
b11 *
1'
b11 ,
b111 #
b111 &
b111 $
#80000
b1000 $
