combinational_circuits/src/priority_enc.v
`timescale 1ns/1ps

module priority_encoder(
    input [3:0] in,
    output reg [1:0] out,
    output reg valid
);

always @(*) begin
    valid = |in;
    if (in[3])
        out = 2'b11;
    else if (in[2])
        out = 2'b10;
    else if (in[1])
        out = 2'b01;
    else if (in[0])
        out = 2'b00;
    else
        out = 2'b00;
end

endmodule

combinational_circuits/tb/tb_priority_enc.v
`timescale 1ns/1ps

module tb_priority_encoder;

reg [3:0] in;
wire [1:0] out;
wire valid;

priority_encoder uut(.in(in), .out(out), .valid(valid));

initial begin
    $dumpfile("priority_encoder.vcd");
    $dumpvars(0, tb_priority_encoder);

    in = 4'b0000;
    #10 in = 4'b0001;
    #10 in = 4'b0010;
    #10 in = 4'b0011;
    #10 in = 4'b0100;
    #10 in = 4'b0110;
    #10 in = 4'b1000;
    #10 in = 4'b1011;
    #10 $finish;
end

endmodule

combinational_circuits/priority_encoder.vcd
$date
	Fri Mar 27 01:01:30 2026
$end
$version
	Icarus Verilog
$end
$timescale
	1ps
$end
$scope module tb_priority_encoder $end
$var wire 1 ! valid $end
$var wire 2 " out [1:0] $end
$var reg 4 # in [3:0] $end
$scope module uut $end
$var wire 4 $ in [3:0] $end
$var reg 2 % out [1:0] $end
$var reg 1 ! valid $end
$upscope $end
$upscope $end
$enddefinitions $end
$comment Show the parameter values. $end
$dumpall
$end
#0
$dumpvars
b0 %
b0 $
b0 #
b0 "
0!
$end
#10000
1!
b1 #
b1 $
#20000
b1 "
b1 %
b10 #
b10 $
#30000
b11 #
b11 $
#40000
b10 "
b10 %
b100 #
b100 $
#50000
b110 #
b110 $
#60000
b11 "
b11 %
b1000 #
b1000 $
#70000
b1011 #
b1011 $
