combinational_circuits/src/priority_enc_4to2.v
// ============================================================
// 4-to-2 Priority Encoder with Valid (V) output
// Priority: I[3] > I[2] > I[1] > I[0]
// V=0 when no input is active
// ============================================================
module priority_enc_4to2 (
    input  [3:0] I,
    output reg [1:0] Y,
    output reg       V   // valid bit
);
    always @(*) begin
        casez (I)
            4'b1???:  begin Y = 2'b11; V = 1'b1; end
            4'b01??:  begin Y = 2'b10; V = 1'b1; end
            4'b001?:  begin Y = 2'b01; V = 1'b1; end
            4'b0001:  begin Y = 2'b00; V = 1'b1; end
            default:  begin Y = 2'b00; V = 1'b0; end
        endcase
    end
endmodule

combinational_circuits/tb/tb_priority_enc_4to2.v
`timescale 1ns/1ps
module tb_priority_enc_4to2;
    reg  [3:0] I;
    wire [1:0] Y;
    wire       V;

    priority_enc_4to2 uut (.I(I), .Y(Y), .V(V));

    integer i;
    initial begin
        $dumpfile("priority_enc_4to2.vcd");
        $dumpvars(0, tb_priority_enc_4to2);
        $display("I       | Y  | V");
        $display("--------|----|-");
        for (i = 0; i < 16; i = i + 1) begin
            I = i; #10;
            $display("%b | %b | %b", I, Y, V);
        end
        $finish;
    end
endmodule

combinational_circuits/priority_enc_4to2.vcd
$date
	Sun Apr 12 19:43:19 2026
$end
$version
	Icarus Verilog
$end
$timescale
	1ps
$end
$scope module tb_priority_enc_4to2 $end
$var wire 2 ! Y [1:0] $end
$var wire 1 " V $end
$var reg 4 # I [3:0] $end
$var integer 32 $ i [31:0] $end
$scope module uut $end
$var wire 4 % I [3:0] $end
$var reg 1 " V $end
$var reg 2 & Y [1:0] $end
$upscope $end
$upscope $end
$enddefinitions $end
$comment Show the parameter values. $end
$dumpall
$end
#0
$dumpvars
b0 &
b0 %
b0 $
b0 #
0"
b0 !
$end
#10000
1"
b1 #
b1 %
b1 $
#20000
b1 !
b1 &
b10 #
b10 %
b10 $
#30000
b11 #
b11 %
b11 $
#40000
b10 !
b10 &
b100 #
b100 %
b100 $
#50000
b101 #
b101 %
b101 $
#60000
b110 #
b110 %
b110 $
#70000
b111 #
b111 %
b111 $
#80000
b11 !
b11 &
b1000 #
b1000 %
b1000 $
#90000
b1001 #
b1001 %
b1001 $
#100000
b1010 #
b1010 %
b1010 $
#110000
b1011 #
b1011 %
b1011 $
#120000
b1100 #
b1100 %
b1100 $
#130000
b1101 #
b1101 %
b1101 $
#140000
b1110 #
b1110 %
b1110 $
#150000
b1111 #
b1111 %
b1111 $
#160000
b10000 $
