sequential/src/counter4bit.v
`timescale 1ns/1ps

module counter4(
    input clk,
    input rst,
    output reg [3:0] q
);

always @(posedge clk or posedge rst) begin
    if (rst)
        q <= 0;
    else
        q <= q + 1;
end

endmodule

sequential/tb/tb_counter4bit.v
`timescale 1ns/1ps

module tb_counter4;

reg clk, rst;
wire [3:0] q;

counter4 uut (.clk(clk), .rst(rst), .q(q));

initial clk = 0;
always #5 clk = ~clk;


initial begin
    $dumpfile("counter4.vcd");
    $dumpvars(0, tb_counter4);

    rst = 1;
    #10 rst = 0;
    #100 $finish;
end

endmodule

sequential/counter4.vcd
$date
	Thu Mar 26 23:56:45 2026
$end
$version
	Icarus Verilog
$end
$timescale
	1ps
$end
$scope module tb_counter4 $end
$var wire 4 ! q [3:0] $end
$var reg 1 " clk $end
$var reg 1 # rst $end
$scope module uut $end
$var wire 1 " clk $end
$var wire 1 # rst $end
$var reg 4 $ q [3:0] $end
$upscope $end
$upscope $end
$enddefinitions $end
$comment Show the parameter values. $end
$dumpall
$end
#0
$dumpvars
b0 $
1#
0"
b0 !
$end
#5000
1"
#10000
0"
0#
#15000
b1 !
b1 $
1"
#20000
0"
#25000
b10 !
b10 $
1"
#30000
0"
#35000
b11 !
b11 $
1"
#40000
0"
#45000
b100 !
b100 $
1"
#50000
0"
#55000
b101 !
b101 $
1"
#60000
0"
#65000
b110 !
b110 $
1"
#70000
0"
#75000
b111 !
b111 $
1"
#80000
0"
#85000
b1000 !
b1000 $
1"
#90000
0"
#95000
b1001 !
b1001 $
1"
#100000
0"
#105000
b1010 !
b1010 $
1"
