sequential/src/dff.v
module dff(input clk,rst,d,output reg q);
always @(posedge clk or posedge rst)begin
	if(rst)
		q<=0;
	else
		q<=d;
end
endmodule

sequential/tb/tb_dff.v
module tb_dff;
reg clk,rst,d;
wire q;

dff uut(.clk(clk),.rst(rst),.d(d),.q(q));
always #5 clk=~clk;
initial begin
	$dumpfile("dff.vcd");
	$dumpvars(0,tb_dff);
       	$monitor("d=%b | q=%b |clk=%t |rst=%b",d,q,clk,rst);
	rst=1;clk=0;d=0;
	#10 rst=0;d=0;
	#10 d=1;
	#10 d=0;
	#10 d=1;
	#10 $finish;
	end
endmodule

sequential/dff.vcd
$date
	Thu Mar 26 16:43:33 2026
$end
$version
	Icarus Verilog
$end
$timescale
	1s
$end
$scope module tb_dff $end
$var wire 1 ! q $end
$var reg 1 " clk $end
$var reg 1 # d $end
$var reg 1 $ rst $end
$scope module uut $end
$var wire 1 " clk $end
$var wire 1 # d $end
$var wire 1 $ rst $end
$var reg 1 ! q $end
$upscope $end
$upscope $end
$enddefinitions $end
$comment Show the parameter values. $end
$dumpall
$end
#0
$dumpvars
1$
0#
0"
0!
$end
#5
1"
#10
0"
0$
#15
1"
#20
0"
1#
#25
1!
1"
#30
0"
0#
#35
0!
1"
#40
0"
1#
#45
1!
1"
