sequential/src/pipo.v
module pipo(input [3:0]pin,input clk,rst,load,output reg [3:0]out);

always @(posedge clk or posedge rst)begin
	if(rst)
		out<=4'b0000;
	else if(load)
		out<=pin;
		
	else
		out<={out[2:0],1'b0};
	end
endmodule

sequential/tb/tb_pipo.v
module tb_pipo;
reg [3:0]pin;
reg clk,rst,load;
wire [3:0]out;

pipo uut(.pin(pin),.out(out),.clk(clk),.rst(rst),.load(load));

always #5 clk=~clk;

initial begin
	$dumpfile("pipo.vcd");
	$dumpvars(0,tb_pipo);
	clk=0;rst=1;
	#10 rst=0;load=1;
	#10 pin=4'b1000;
	#40; 
	#10 rst=1;
	#10 rst=0;load=1;
	#10 pin=4'b0001;
	#50 $finish;
	end
endmodule

sequential/pipo.vcd
$date
	Fri Mar 27 00:49:32 2026
$end
$version
	Icarus Verilog
$end
$timescale
	1s
$end
$scope module tb_pipo $end
$var wire 4 ! out [3:0] $end
$var reg 1 " clk $end
$var reg 1 # load $end
$var reg 4 $ pin [3:0] $end
$var reg 1 % rst $end
$scope module uut $end
$var wire 1 " clk $end
$var wire 1 # load $end
$var wire 4 & pin [3:0] $end
$var wire 1 % rst $end
$var reg 4 ' out [3:0] $end
$upscope $end
$upscope $end
$enddefinitions $end
$comment Show the parameter values. $end
$dumpall
$end
#0
$dumpvars
b0 '
bx &
1%
bx $
x#
0"
b0 !
$end
#5
1"
#10
0"
1#
0%
#15
bx !
bx '
1"
#20
0"
b1000 $
b1000 &
#25
b1000 !
b1000 '
1"
#30
0"
#35
1"
#40
0"
#45
1"
#50
0"
#55
1"
#60
0"
#65
1"
#70
b0 !
b0 '
0"
1%
#75
1"
#80
0"
0%
#85
b1000 !
b1000 '
1"
#90
0"
b1 $
b1 &
#95
b1 !
b1 '
1"
