sequential/src/piso.v
`timescale 1ns/1ps

module piso(
    input clk,
    input rst,
    input load,          
    input [3:0] parallel_in, 
    output reg serial_out
);

reg [3:0] q;

always @(posedge clk or posedge rst) begin
    if (rst) begin
        q <= 0;
        serial_out <= 0;
    end else if (load) begin
        q <= parallel_in;     
        serial_out <= parallel_in[3]; 
    end else begin
        q <= {q[2:0], 1'b0}; 
        serial_out <= q[3];   
    end
end

endmodule

sequential/tb/tb_piso.v
`timescale 1ns/1ps

module tb_piso;

reg clk, rst, load;
reg [3:0] parallel_in;
wire serial_out;

piso uut (
    .clk(clk),
    .rst(rst),
    .load(load),
    .parallel_in(parallel_in),
    .serial_out(serial_out)
);

initial clk = 0;
always #5 clk = ~clk;

initial begin
    $dumpfile("piso.vcd");
    $dumpvars(0, tb_piso);

    rst = 1;
    load = 0;
    parallel_in = 4'b1011;
    #10 rst = 0;

    load = 1;
    #10 load = 0;
    #40;

    parallel_in = 4'b1101;
    load = 1;
    #10 load = 0;
    #40;

    $finish;
end

endmodule

sequential/piso.vcd
$date
	Fri Mar 27 00:28:55 2026
$end
$version
	Icarus Verilog
$end
$timescale
	1ps
$end
$scope module tb_piso $end
$var wire 1 ! serial_out $end
$var reg 1 " clk $end
$var reg 1 # load $end
$var reg 4 $ parallel_in [3:0] $end
$var reg 1 % rst $end
$scope module uut $end
$var wire 1 " clk $end
$var wire 1 # load $end
$var wire 4 & parallel_in [3:0] $end
$var wire 1 % rst $end
$var reg 4 ' q [3:0] $end
$var reg 1 ! serial_out $end
$upscope $end
$upscope $end
$enddefinitions $end
$comment Show the parameter values. $end
$dumpall
$end
#0
$dumpvars
b0 '
b1011 &
1%
b1011 $
0#
0"
0!
$end
#5000
1"
#10000
0"
1#
0%
#15000
1!
b1011 '
1"
#20000
0"
0#
#25000
b110 '
1"
#30000
0"
#35000
0!
b1100 '
1"
#40000
0"
#45000
1!
b1000 '
1"
#50000
0"
#55000
b0 '
1"
#60000
0"
1#
b1101 $
b1101 &
#65000
b1101 '
1"
#70000
0"
0#
#75000
b1010 '
1"
#80000
0"
#85000
b100 '
1"
#90000
0"
#95000
0!
b1000 '
1"
#100000
0"
#105000
1!
b0 '
1"
