sequential/src/sipo.v
`timescale 1ns/1ps

module sipo(
    input clk,
    input rst,
    input serial_in,
    output reg [3:0] parallel_out
);

always @(posedge clk or posedge rst) begin
    if (rst)
        parallel_out <= 0;
    else
        parallel_out <= {parallel_out[2:0], serial_in}; 
end

endmodule

sequential/tb/tb_sipo.v
`timescale 1ns/1ps

module tb_sipo;

reg clk, rst, serial_in;
wire [3:0] parallel_out;

sipo uut (.clk(clk), .rst(rst), .serial_in(serial_in), .parallel_out(parallel_out));

initial clk = 0;
always #5 clk = ~clk;

initial begin
    $dumpfile("sipo.vcd");
    $dumpvars(0, tb_sipo);

    rst = 1; serial_in = 0;
    #10 rst = 0;
    serial_in = 1; #10;
    serial_in = 0; #10;
    serial_in = 1; #10;
    serial_in = 1; #10;
    #20 $finish;
end

endmodule

sequential/sipo.vcd
$date
	Fri Mar 27 00:09:02 2026
$end
$version
	Icarus Verilog
$end
$timescale
	1ps
$end
$scope module tb_sipo $end
$var wire 4 ! parallel_out [3:0] $end
$var reg 1 " clk $end
$var reg 1 # rst $end
$var reg 1 $ serial_in $end
$scope module uut $end
$var wire 1 " clk $end
$var wire 1 # rst $end
$var wire 1 $ serial_in $end
$var reg 4 % parallel_out [3:0] $end
$upscope $end
$upscope $end
$enddefinitions $end
$comment Show the parameter values. $end
$dumpall
$end
#0
$dumpvars
b0 %
0$
1#
0"
b0 !
$end
#5000
1"
#10000
0"
1$
0#
#15000
b1 !
b1 %
1"
#20000
0"
0$
#25000
b10 !
b10 %
1"
#30000
0"
1$
#35000
b101 !
b101 %
1"
#40000
0"
#45000
b1011 !
b1011 %
1"
#50000
0"
#55000
b111 !
b111 %
1"
#60000
0"
#65000
b1111 !
b1111 %
1"
