sequential/src/siso.v
`timescale 1ns/1ps

module siso(
    input clk,
    input rst,
    input serial_in,
    output wire serial_out
);

reg [3:0] q;  

always @(posedge clk or posedge rst) begin
    if (rst)
        q <= 0;
    else
        q <= {q[2:0], serial_in};
end

assign serial_out = q[3];  
endmodule

sequential/tb/tb_siso.v
`timescale 1ns/1ps

module tb_siso;

reg clk, rst, serial_in;
wire serial_out;

siso uut (.clk(clk), .rst(rst), .serial_in(serial_in), .serial_out(serial_out));

initial clk = 0;
always #5 clk = ~clk;

initial begin
    $dumpfile("siso.vcd");
    $dumpvars(0, tb_siso);

    rst = 1; serial_in = 0;
    #10 rst = 0;
    serial_in = 1; #10;
    serial_in = 0; #10;
    serial_in = 1; #10;
    serial_in = 1; #10;
    #20 $finish;
end

endmodule

sequential/siso.vcd
$date
	Fri Mar 27 00:05:04 2026
$end
$version
	Icarus Verilog
$end
$timescale
	1ps
$end
$scope module tb_siso $end
$var wire 1 ! serial_out $end
$var reg 1 " clk $end
$var reg 1 # rst $end
$var reg 1 $ serial_in $end
$scope module uut $end
$var wire 1 " clk $end
$var wire 1 # rst $end
$var wire 1 $ serial_in $end
$var wire 1 ! serial_out $end
$var reg 4 % q [3:0] $end
$upscope $end
$upscope $end
$enddefinitions $end
$comment Show the parameter values. $end
$dumpall
$end
#0
$dumpvars
b0 %
0$
1#
0"
0!
$end
#5000
1"
#10000
0"
1$
0#
#15000
b1 %
1"
#20000
0"
0$
#25000
b10 %
1"
#30000
0"
1$
#35000
b101 %
1"
#40000
0"
#45000
1!
b1011 %
1"
#50000
0"
#55000
0!
b111 %
1"
#60000
0"
#65000
1!
b1111 %
1"
