combinational_circuits/src/mux2_1_gl.v
`timescale 1ns/1ps
module mux2_1_gl(input a,b,s,output y);
wire ns,w,x;
not g1(ns,s);
and g2(w,ns,a);
and g3(x,s,b);
or g4(y,w,x);
endmodule

combinational_circuits/tb/tb_mux2_1_gl.v
`timescale 1ns/1ps
module tb_mux2_1_gl;
reg a,b,s;
wire y;

mux2_1_gl uut1(a,b,s,y);


initial begin
	$dumpfile("sim/mux2_1_gl.vcd");
	$dumpvars(0,tb_mux2_1_gl );
	$display("2_to_1_MUX Output");
	$monitor("a=%b b=%b s=%b y=%b",a,b,s,y);
	a=0; b=0; s=0;
  	#10 a=0; b=0; s=1;
  	#10 a=0; b=1; s=0;
  	#10 a=0; b=1; s=1;
  	#10 a=1; b=0; s=0;
  	#10 a=1; b=0; s=1;
  	#10 a=1; b=1; s=0;
  	#10 a=1; b=1; s=1;

  	#10 $finish;
end

endmodule

combinational_circuits/sim/mux2_1_gl.vcd
$date
	Thu Mar 26 15:14:11 2026
$end
$version
	Icarus Verilog
$end
$timescale
	1ps
$end
$scope module tb_mux2_1_gl $end
$var wire 1 ! y $end
$var reg 1 " a $end
$var reg 1 # b $end
$var reg 1 $ s $end
$scope module uut1 $end
$var wire 1 " a $end
$var wire 1 # b $end
$var wire 1 % ns $end
$var wire 1 $ s $end
$var wire 1 & w $end
$var wire 1 ' x $end
$var wire 1 ! y $end
$upscope $end
$upscope $end
$enddefinitions $end
$comment Show the parameter values. $end
$dumpall
$end
#0
$dumpvars
0'
0&
1%
0$
0#
0"
0!
$end
#10000
0%
1$
#20000
1%
0$
1#
#30000
1!
0%
1'
1$
#40000
1&
1!
1%
0'
0$
0#
1"
#50000
0!
0&
0%
1$
#60000
1!
1&
1%
0$
1#
#70000
0&
0%
1'
1$
