FSM/src/mealy_1101.v
module mealy_1101(input clk,rst,x,output reg z);
parameter [1:0]s0=2'b00,s1=2'b01,s2=2'b10,s3=2'b11;

reg[1:0]cs,ns;
always @(posedge clk or posedge rst)begin
	if(rst)
		cs<=2'b00;
	else
		cs<=ns;
end

always @(*)begin
	z=0;
	case(cs)
		s0:if(x)
			ns=s1;
		   else
			ns=s0;
		s1:if(x)
			ns=s2;
		   else
			ns=s0;
		s2:if(x)
			ns=s2;
		   else
			ns=s3;
		s3:if(x)begin
			z=1;
			ns=s1;
		   end else
		        ns=s0;
		default:ns=s0;
	endcase
end
endmodule

FSM/tb/tb_mealy_1101.v
module tb_mealy_1101;
reg clk,rst,x;
wire z;

mealy_1101 uut(.clk(clk),.rst(rst),.x(x),.z(z));

always #5 clk=~clk;

initial begin
	$dumpfile("mealy_1101.vcd");
	$dumpvars(0,tb_mealy_1101);
	
	clk=0;rst=1;x=0;
	#10 rst=0;
	#10 x=1;
	#10 x=1;
	#10 x=0;
	#10 x=1;
	
	#10 x=1;//overlapping 
	#10 x=0;
	#10 x=1;
	
	$monitor("clk=%t | rst=%b | x=%b | z=%b",clk,rst,x,z);
	#20 $finish;
end
endmodule

FSM/mealy_1101.vcd
$date
	Fri Mar 27 16:38:36 2026
$end
$version
	Icarus Verilog
$end
$timescale
	1s
$end
$scope module tb_mealy_1101 $end
$var wire 1 ! z $end
$var reg 1 " clk $end
$var reg 1 # rst $end
$var reg 1 $ x $end
$scope module uut $end
$var wire 1 " clk $end
$var wire 1 # rst $end
$var wire 1 $ x $end
$var parameter 2 % s0 $end
$var parameter 2 & s1 $end
$var parameter 2 ' s2 $end
$var parameter 2 ( s3 $end
$var reg 2 ) cs [1:0] $end
$var reg 2 * ns [1:0] $end
$var reg 1 ! z $end
$upscope $end
$upscope $end
$enddefinitions $end
$comment Show the parameter values. $end
$dumpall
b11 (
b10 '
b1 &
b0 %
$end
#0
$dumpvars
b0 *
b0 )
0$
1#
0"
0!
$end
#5
1"
#10
0"
0#
#15
1"
#20
b1 *
0"
1$
#25
b10 *
b1 )
1"
#30
0"
#35
b10 )
1"
#40
b11 *
0"
0$
#45
b0 *
b11 )
1"
#50
b1 *
1!
0"
1$
#55
b10 *
0!
b1 )
1"
#60
0"
#65
b10 )
1"
#70
b11 *
0"
0$
#75
b0 *
b11 )
1"
#80
b1 *
1!
0"
1$
#85
b10 *
0!
b1 )
1"
#90
0"
#95
b10 )
1"
